gitutils/__init__.py
gitutils/cmdline.py
gitutils/gitclone.py
gitutils/githubs.py
gitutils/gitsync.py
gitutils/templates/index.html
gitutils/utils/__init__.py
xgit_utils-1.4.2.dist-info/METADATA
xgit_utils-1.4.2.dist-info/WHEEL
xgit_utils-1.4.2.dist-info/entry_points.txt
xgit_utils-1.4.2.dist-info/top_level.txt
xgit_utils-1.4.2.dist-info/RECORD
