Metadata-Version: 2.1
Name: xgit-utils
Version: 1.4.2
Summary: Git repository management tool
Author-email: seven <1162584980@qq.com>
License: MIT License
Classifier: Topic :: Utilities
Classifier: Programming Language :: Python :: 3
Classifier: License :: OSI Approved :: MIT License
Classifier: Operating System :: OS Independent
Classifier: Environment :: Console :: Curses
Requires-Python: >=3.8
Requires-Dist: PyGithub==v2.4.0
Requires-Dist: click
Requires-Dist: types-click
Requires-Dist: tqdm
Requires-Dist: types-tqdm
Requires-Dist: pydantic
Provides-Extra: dev
Requires-Dist: build; extra == "dev"
Requires-Dist: twine; extra == "dev"
Provides-Extra: pyinstaller
Requires-Dist: pyinstaller>=6.10.0; extra == "pyinstaller"
Provides-Extra: py2exe
Requires-Dist: py2exe>=0.12; extra == "py2exe"
